setup.cfg
setup.py
bilib/__init__.py
bilib/crash_on_ipy.py
bilib/debug_utils.py
bilib/file_utils.py
bilib/logging_utils.py
bilib/misc_utils.py
bilib/numeric_utils.py
bilib/numpy_utils.py
bilib/vis_utils.py
bilib/visualization_utils.py
bilib.egg-info/PKG-INFO
bilib.egg-info/SOURCES.txt
bilib.egg-info/dependency_links.txt
bilib.egg-info/not-zip-safe
bilib.egg-info/requires.txt
bilib.egg-info/top_level.txt