Metadata-Version: 1.0
Name: bilib
Version: 0.2.1
Summary: Bily's personal library
Home-page: UNKNOWN
Author: Bily Lee
Author-email: bily.lee@qq.com
License: MIT
Platform: UNKNOWN
